mkbak/__init__.py
mkbak/__main__.py
mkbak/mkbak_args/__init__.py
mkbak-1.3.2.dist-info/LICENSE
mkbak-1.3.2.dist-info/METADATA
mkbak-1.3.2.dist-info/WHEEL
mkbak-1.3.2.dist-info/entry_points.txt
mkbak-1.3.2.dist-info/top_level.txt
mkbak-1.3.2.dist-info/RECORD
