Metadata-Version: 2.1
Name: mkbak
Version: 1.3.2
Summary: a commandline utility to create file backups
Home-page: https://github.com/sudo-julia/mkbak
Author: Julia A M
Author-email: jlearning@tuta.io
License: UNKNOWN
Platform: UNKNOWN
Classifier: Development Status :: 5 - Production/Stable
Classifier: Environment :: Console
Classifier: Intended Audience :: End Users/Desktop
Classifier: License :: OSI Approved :: GNU General Public License v3 (GPLv3)
Classifier: Natural Language :: English
Classifier: Operating System :: POSIX :: Linux
Classifier: Programming Language :: Python :: 3.7
Classifier: Programming Language :: Python :: 3.8
Classifier: Programming Language :: Python :: 3.9
Classifier: Topic :: System :: Archiving :: Backup
Classifier: Topic :: Terminals
Requires-Python: >=3.7
Requires-Dist: mkbak-iterfzf (>=0.7)
Requires-Dist: rich (>=9.8.2)
